scoutcipher/__init__.py
scoutcipher/base.py
scoutcipher/codes/__init__.py
scoutcipher/codes/grid.py
scoutcipher/codes/invert_alph.py
scoutcipher/codes/keyword.py
scoutcipher/codes/morse.py
scoutcipher/codes/murcielago.py
scoutcipher/codes/reverse.py
ScoutCipher-0.1.0.dist-info/LICENSE
ScoutCipher-0.1.0.dist-info/METADATA
ScoutCipher-0.1.0.dist-info/WHEEL
ScoutCipher-0.1.0.dist-info/top_level.txt
ScoutCipher-0.1.0.dist-info/RECORD
