Metadata-Version: 2.2
Name: ScoutCipher
Version: 0.1.0
Summary: ScoutCipher is a Python package for encrypting and decrypting messages using different encryption methods using scout codes.
Home-page: https://github.com/NievasGustavo/ScoutCipher
Author: Gustavo Nievas
License: MIT
Classifier: Programming Language :: Python :: 3
Classifier: Programming Language :: Python :: 3.10
Classifier: Programming Language :: Python :: 3.11
Classifier: Programming Language :: Python :: 3.12
Classifier: License :: OSI Approved :: MIT License
Classifier: Operating System :: OS Independent
Requires-Python: >=3.10
License-File: LICENSE
Dynamic: author
Dynamic: classifier
Dynamic: description
Dynamic: description-content-type
Dynamic: home-page
Dynamic: license
Dynamic: requires-python
Dynamic: summary
